<?xml version="1.0" encoding="utf-8" ?><dwsync><file name="0-lrg.jpg" server="ftp.wild4life.org" local="3445282329" remote="42099983964" /><file name="0.jpg" server="ftp.wild4life.org" local="3445282374" remote="24920114780" /><file name="1-lrg.jpg" server="ftp.wild4life.org" local="3445282554" remote="42099983964" /><file name="1.jpg" server="ftp.wild4life.org" local="3445282572" remote="24920114780" /><file name="2-lrg.jpg" server="ftp.wild4life.org" local="3445283085" remote="42099983964" /><file name="2.jpg" server="ftp.wild4life.org" local="3445283113" remote="24920114780" /><file name="3-lrg.jpg" server="ftp.wild4life.org" local="3445283349" remote="42099983964" /><file name="3.jpg" server="ftp.wild4life.org" local="3445283364" remote="24920114780" /><file name="4-lrg.jpg" server="ftp.wild4life.org" local="3445283691" remote="42099983964" /><file name="4.jpg" server="ftp.wild4life.org" local="3445283724" remote="24920114780" /><file name="5-lrg.jpg" server="ftp.wild4life.org" local="3445283878" remote="42099983964" /><file name="5.jpg" server="ftp.wild4life.org" local="3445283889" remote="24920114780" /><file name="6-lrg.jpg" server="ftp.wild4life.org" local="3445284363" remote="42099983964" /><file name="6.jpg" server="ftp.wild4life.org" local="3445284380" remote="24920114780" /><file name="7-lrg.jpg" server="ftp.wild4life.org" local="3445284778" remote="42099983964" /><file name="7.jpg" server="ftp.wild4life.org" local="3445284782" remote="24920114780" /><file name="8-lrg.jpg" server="ftp.wild4life.org" local="3392769600" remote="42099983964" /><file name="8.jpg" server="ftp.wild4life.org" local="3392769600" remote="24920114780" /></dwsync>