<?xml version="1.0" encoding="utf-8" ?><dwsync><file name="bg.jpg" server="ftp.smoller.com//public_html/client/wild4life/" local="3380130734" remote="29158392936" /><file name="bg_last.jpg" server="ftp.smoller.com//public_html/client/wild4life/" local="3380130763" remote="50633229416" /><file name="image_1_fpo.gif" server="ftp.smoller.com//public_html/client/wild4life/" local="3380130907" remote="67813098600" /><file name="image_2_fpo.gif" server="ftp.smoller.com//public_html/client/wild4life/" local="3380130907" remote="67813098600" /><file name="image_3_fpo.gif" server="ftp.smoller.com//public_html/client/wild4life/" local="3380130907" remote="67813098600" /><file name="image_4_fpo.gif" server="ftp.smoller.com//public_html/client/wild4life/" local="3380130907" remote="67813098600" /><file name="1.jpg" server="ftp.smoller.com//public_html/client/wild4life/" local="3389128096" remote="417440965948452908" /><file name="2.jpg" server="ftp.smoller.com//public_html/client/wild4life/" local="3389128670" remote="417440965948452908" /><file name="3.jpg" server="ftp.smoller.com//public_html/client/wild4life/" local="3389128507" remote="417440965948452908" /><file name="4.jpg" server="ftp.smoller.com//public_html/client/wild4life/" local="3389128307" remote="417440965948452908" /><file name="5.jpg" server="ftp.smoller.com//public_html/client/wild4life/" local="3389130228" remote="417440965948452908" /></dwsync>